src/imessage_github_relay/__init__.py
src/imessage_github_relay/_internal.py
src/imessage_github_relay/utils/__init__.py
src/imessage_github_relay/utils/_internet.py
src/imessage_github_relay/utils/_internet.pyi
src/imessage_github_relay/utils/_term_color_fix_win.py
src/imessage_github_relay/utils/_term_color_fix_win.pyi
src/imessage_github_relay/utils/_toml.py
src/imessage_github_relay/utils/_toml.pyi
imessage_github_relay-0.1.1.dist-info/LICENSE
imessage_github_relay-0.1.1.dist-info/METADATA
imessage_github_relay-0.1.1.dist-info/WHEEL
imessage_github_relay-0.1.1.dist-info/top_level.txt
imessage_github_relay-0.1.1.dist-info/RECORD
