Metadata-Version: 2.1
Name: imessage-github-relay
Version: 0.1.1
Summary: iMessage send-refresh-recieve messages OS independently through a GitHub Actions Relay.
Author-email: Soumyo Deep Gupta <deep.main.ac@gmail.com>
Maintainer-email: Soumyo Deep Gupta <deep.main.ac@gmail.com>
License: MIT License
Project-URL: GitHub, https://github.com/d33p0st/iMessage-github-relay
Project-URL: Issues, https://github.com/d33p0st/iMessage-github-relay/issues
Project-URL: Pull Requests, https://github.com/d33p0st/iMessage-github-relay/pulls
Keywords: d33p0st,iMessage,relay,github,python
Classifier: Development Status :: 4 - Beta
Classifier: Topic :: Software Development :: Libraries :: Python Modules
Classifier: Programming Language :: Python :: 3.8
Classifier: Programming Language :: Python :: 3.9
Classifier: Programming Language :: Python :: 3.10
Classifier: Programming Language :: Python :: 3.11
Classifier: Programming Language :: Python :: 3.12
Classifier: Programming Language :: Python :: 3.13
Classifier: License :: OSI Approved :: MIT License
Classifier: Operating System :: OS Independent
Requires-Python: >=3.8
License-File: LICENSE
Requires-Dist: toml
Requires-Dist: colorama
Requires-Dist: requests
